webpage_searcher/__init__.py
webpage_searcher/finders/__init__.py
webpage_searcher/finders/finder.py
webpage_searcher/finders/phrase/__init__.py
webpage_searcher/finders/phrase/handlers.py
webpage_searcher/finders/phrase/phrase_finder.py
webpage_searcher/finders/result.py
webpage_searcher/finders/url/__init__.py
webpage_searcher/finders/url/url_finder.py
webpage_searcher/outputs/__init__.py
webpage_searcher/outputs/ouput.py
webpage_searcher/outputs/print_output.py
webpage_searcher/utils/__init__.py
webpage_searcher/utils/constants.py
webpage_searcher/utils/xpath.py
webpage_searcher-0.0.2.dist-info/METADATA
webpage_searcher-0.0.2.dist-info/WHEEL
webpage_searcher-0.0.2.dist-info/RECORD
