Metadata-Version: 2.1
Name: webpage-searcher
Version: 0.0.2
Summary: hello
Author: john-blmns
Requires-Python: >=3.9,<4
Classifier: Programming Language :: Python :: 3
Classifier: Programming Language :: Python :: 3.9
Classifier: Programming Language :: Python :: 3.10
Classifier: Programming Language :: Python :: 3.11
Requires-Dist: beautifulsoup4 (==4.11.2)
